{
    "objects": [
        {
            "bbox": [
                0.169336,
                0.67526,
                0.337891,
                0.558854
            ],
            "label": 6,
            "name": "PseudoisNayaur"
        },
        {
            "bbox": [
                0.698438,
                0.474479,
                0.603125,
                0.947917
            ],
            "label": 9,
            "name": "stone"
        }
    ],
    "relationships": [
        {
            "subject_id": 0,
            "object_id": 1,
            "predicate": 7
        }
    ],
    "image": "000000010087.jpg"
}