{
    "objects": [
        {
            "bbox": [
                0.542969,
                0.391667,
                0.222396,
                0.312963
            ],
            "label": 0,
            "name": "Pandas"
        },
        {
            "bbox": [
                0.334115,
                0.244907,
                0.218229,
                0.458333
            ],
            "label": 8,
            "name": "tree"
        },
        {
            "bbox": [
                0.586458,
                0.70787,
                0.666667,
                0.230556
            ],
            "label": 11,
            "name": "grass"
        }
    ],
    "relationships": [
        {
            "subject_id": 0,
            "object_id": 2,
            "predicate": 0
        }
    ],
    "image": "000000008449.jpg"
}