{
    "objects": [
        {
            "bbox": [
                0.4845,
                0.790333,
                0.315,
                0.349333
            ],
            "label": 0,
            "name": "Pandas"
        },
        {
            "bbox": [
                0.503875,
                0.617667,
                0.97375,
                0.659333
            ],
            "label": 11,
            "name": "grass"
        }
    ],
    "relationships": [
        {
            "subject_id": 0,
            "object_id": 1,
            "predicate": 1
        }
    ],
    "image": "000000007744.jpg"
}