{
    "objects": [
        {
            "bbox": [
                0.506055,
                0.557292,
                0.113672,
                0.177083
            ],
            "label": 5,
            "name": "porcupine"
        },
        {
            "bbox": [
                0.438672,
                0.363802,
                0.660156,
                0.191146
            ],
            "label": 9,
            "name": "stone"
        },
        {
            "bbox": [
                0.523828,
                0.785937,
                0.774219,
                0.325
            ],
            "label": 9,
            "name": "stone"
        },
        {
            "bbox": [
                0.789258,
                0.651302,
                0.421484,
                0.197396
            ],
            "label": 9,
            "name": "stone"
        },
        {
            "bbox": [
                0.500391,
                0.140885,
                0.999219,
                0.280729
            ],
            "label": 7,
            "name": "forest"
        }
    ],
    "relationships": [
        {
            "subject_id": 0,
            "object_id": 2,
            "predicate": 9
        }
    ],
    "image": "000000003387.jpg"
}