{
    "objects": [
        {
            "bbox": [
                0.525,
                0.703385,
                0.215625,
                0.195312
            ],
            "label": 5,
            "name": "porcupine"
        },
        {
            "bbox": [
                0.624219,
                0.279948,
                0.703125,
                0.555729
            ],
            "label": 7,
            "name": "forest"
        }
    ],
    "relationships": [
        {
            "subject_id": 0,
            "object_id": 1,
            "predicate": 0
        }
    ],
    "image": "000000003884.jpg"
}